pytessel/__init__.py
pytessel/_version.py
pytessel/pytessel_core.cpython-314-x86_64-linux-musl.so
pytessel.libs/libgcc_s-0cd532bd.so.1
pytessel.libs/libgomp-8949ffbe.so.1.0.0
pytessel.libs/libstdc++-5d72f927.so.6.0.33
pytessel-1.3.0.dist-info/METADATA
pytessel-1.3.0.dist-info/WHEEL
pytessel-1.3.0.dist-info/RECORD
pytessel-1.3.0.dist-info/sboms/auditwheel.cdx.json
