Metadata-Version: 2.1
Name: pytessel
Version: 1.3.0
Summary: Python package for building isosurfaces from 3D scalar fields
Author-Email: Ivo Filot <ivo@ivofilot.nl>
License: GPL-3.0-only
Project-URL: Homepage, https://github.com/ifilot/pyqint
Requires-Python: >=3.9
Requires-Dist: numpy
